gaiacalc/__init__.py
gaiacalc/gaiacalc.py
gaiacalc/index.py
gaiacalc/loop.py
gaiacalc/show.py
gaiacalc/util.py
gaiacalc/webserver.py
gaiacalc/data/.DS_Store
gaiacalc/data/DA.grid
gaiacalc/data/DB.grid
gaiacalc/data/bye.html
gaiacalc/data/gaiacalc.png
gaiacalc/data/guide.html
gaiacalc/data/guide.png
gaiacalc/data/install.html
gaiacalc/data/logoUPC.jpg
gaiacalc/data/page.html
gaiacalc/data/question.jpg
gaiacalc/data/quit.jpg
gaiacalc/data/samples.csv
gaiacalc/data/DA/024DA.dat
gaiacalc/data/DA/027DA.dat
gaiacalc/data/DA/032DA.dat
gaiacalc/data/DA/036DA.dat
gaiacalc/data/DA/043DA.dat
gaiacalc/data/DA/045DA.dat
gaiacalc/data/DA/053DA.dat
gaiacalc/data/DA/058DA.dat
gaiacalc/data/DA/066DA.dat
gaiacalc/data/DA/083DA.dat
gaiacalc/data/DA/095DA.dat
gaiacalc/data/DA/09DA.dat
gaiacalc/data/DA/100DA.dat
gaiacalc/data/DA/105DA.dat
gaiacalc/data/DA/110DA.dat
gaiacalc/data/DA/116DA.dat
gaiacalc/data/DA/122DA.dat
gaiacalc/data/DA/129DA.dat
gaiacalc/data/DB/051DB.dat
gaiacalc/data/DB/054DB.dat
gaiacalc/data/DB/058DB.dat
gaiacalc/data/DB/066DB.dat
gaiacalc/data/DB/074DB.dat
gaiacalc/data/DB/087DB.dat
gaiacalc/data/DB/095DB.dat
gaiacalc/data/DB/100DB.dat
gaiacalc/data/DB/110DB.dat
gaiacalc/data/DB/116DB.dat
gaiacalc/data/DB/122DB.dat
gaiacalc/data/DB/129DB.dat
gaiacalc/log/empty.log
gcalc2-0.2.2.dist-info/LICENCE
gcalc2-0.2.2.dist-info/METADATA
gcalc2-0.2.2.dist-info/WHEEL
gcalc2-0.2.2.dist-info/entry_points.txt
gcalc2-0.2.2.dist-info/top_level.txt
gcalc2-0.2.2.dist-info/RECORD
